AGCoder/__init__.py
AGCoder/coder.py
AGCoder/coder_utilities.py
AGCoder-1.0.4.dist-info/LICENSE
AGCoder-1.0.4.dist-info/METADATA
AGCoder-1.0.4.dist-info/WHEEL
AGCoder-1.0.4.dist-info/top_level.txt
AGCoder-1.0.4.dist-info/RECORD
