Metadata-Version: 2.1
Name: AGCoder
Version: 1.0.4
Summary: Code generator class
Author-email: Michael Lundager <michael@wivvies.com>
License: MIT License        
Classifier: Programming Language :: Python :: 3
Classifier: License :: OSI Approved :: MIT License
Classifier: Operating System :: OS Independent
Requires-Python: >=3.7
License-File: LICENSE
